chimeric_tools/Constant.py
chimeric_tools/Data.py
chimeric_tools/Metaculus.py
chimeric_tools/Prepocess.py
chimeric_tools/Spatial.py
chimeric_tools/Time.py
chimeric_tools/__init__.py
chimeric_tools/example.py
chimeric_tools/test.py
chimeric_tools-0.0.3.dist-info/LICENSE
chimeric_tools-0.0.3.dist-info/METADATA
chimeric_tools-0.0.3.dist-info/WHEEL
chimeric_tools-0.0.3.dist-info/top_level.txt
chimeric_tools-0.0.3.dist-info/RECORD
