Metadata-Version: 2.1
Name: chimeric-tools
Version: 0.0.3
Summary: ComputationalUncertaintyLab/chimeric-tools
Home-page: https://github.com/computationalUncertaintyLab/chimeric-tools
Author: WENXUAN YE
Author-email: lehighwenxuanye@gmail.com
Classifier: Programming Language :: Python :: 3
Classifier: License :: OSI Approved :: MIT License
Classifier: Operating System :: OS Independent
Requires-Python: >=3.6
License-File: LICENSE
